<Properties StartupConfiguration="{70FFBC71-9A72-B089-910C-61580AF9F44C}|Unit Tests">
  <MonoDevelop.Ide.Workspace ActiveConfiguration="Debug" />
  <MultiItemStartupConfigurations />
  <MonoDevelop.Ide.DebuggingService.Breakpoints>
    <BreakpointStore />
  </MonoDevelop.Ide.DebuggingService.Breakpoints>
  <MonoDevelop.Ide.ItemProperties.Assembly-CSharp PreferredExecutionTarget="MonoDevelop.Default" />
  <MonoDevelop.Ide.Workbench ActiveDocument="Assets/Collectable.cs">
    <Files>
      <File FileName="Assets/Scripts/PlayerController.cs" Line="84" Column="51" />
      <File FileName="Assets/Scripts/CodePanel.cs" Line="100" Column="26" />
      <File FileName="Assets/Collectable.cs" Line="1" Column="1" />
    </Files>
    <Pads>
      <Pad Id="ProjectPad">
        <State name="__root__">
          <Node name="PrimarySchoolCodingGame" expanded="True">
            <Node name="Assembly-CSharp" expanded="True">
              <Node name="Assets" expanded="True">
                <Node name="Scripts" expanded="True">
                  <Node name="PlayerController.cs" selected="True" />
                </Node>
              </Node>
            </Node>
          </Node>
        </State>
      </Pad>
      <Pad Id="MonoDevelop.Debugger.WatchPad">
        <State />
      </Pad>
      <Pad Id="MonoDevelop.UnitTesting.TestPad">
        <State name="__root__">
          <Node name="PrimarySchoolCodingGame" expanded="True" selected="True" />
        </State>
      </Pad>
    </Pads>
  </MonoDevelop.Ide.Workbench>
  <MonoDevelop.Ide.DebuggingService.PinnedWatches />
</Properties>